MANIFEST.in
setup.py
conjugar/acentuacion.py
conjugar/araq.py
conjugar/conjugar.py
conjugar/symmtera.py
conjugar.egg-info/PKG-INFO
conjugar.egg-info/SOURCES.txt
conjugar.egg-info/dependency_links.txt
conjugar.egg-info/entry_points.txt
conjugar.egg-info/top_level.txt
conjugar/Images/dummp
conjugar/Images/get_stress.0.png
conjugar/Images/show_stress.0.png
conjugar/ReadMeDetailed/dummy
conjugar/ReadMeDetailed/example.rst
conjugar/__pycache__/__init__.cpython-36.pyc
conjugar/__pycache__/acentuacion.cpython-36.pyc
conjugar/__pycache__/araq.cpython-36.pyc
conjugar/__pycache__/symmtera.cpython-36.pyc
conjugar/bin/__init__.py
conjugar/bin/es_sila.py
conjugar/bin/es_verb_list.py
conjugar/bin/es_word_conjugar.py
conjugar/data/conjugar.crtable.json